bayesline/api/__init__.py
bayesline/api/py.typed
bayesline/api/types.py
bayesline/api/_src/__init__.py
bayesline/api/_src/_utils.py
bayesline/api/_src/acl_models.py
bayesline/api/_src/api.py
bayesline/api/_src/maintenance.py
bayesline/api/_src/permissions.py
bayesline/api/_src/registry.py
bayesline/api/_src/settings.py
bayesline/api/_src/settings_types.py
bayesline/api/_src/tasks.py
bayesline/api/_src/types.py
bayesline/api/_src/equity/__init__.py
bayesline/api/_src/equity/api.py
bayesline/api/_src/equity/calendar.py
bayesline/api/_src/equity/calendar_settings.py
bayesline/api/_src/equity/exposure.py
bayesline/api/_src/equity/exposure_settings.py
bayesline/api/_src/equity/ids.py
bayesline/api/_src/equity/modelconstruction.py
bayesline/api/_src/equity/modelconstruction_settings.py
bayesline/api/_src/equity/portfolio.py
bayesline/api/_src/equity/portfolio_settings.py
bayesline/api/_src/equity/portfoliohierarchy.py
bayesline/api/_src/equity/portfoliohierarchy_settings.py
bayesline/api/_src/equity/portfolioreport.py
bayesline/api/_src/equity/report_settings.py
bayesline/api/_src/equity/riskdataset.py
bayesline/api/_src/equity/riskdataset_settings.py
bayesline/api/_src/equity/riskmodels.py
bayesline/api/_src/equity/riskmodels_settings.py
bayesline/api/_src/equity/settings.py
bayesline/api/_src/equity/settings_types.py
bayesline/api/_src/equity/universe.py
bayesline/api/_src/equity/universe_settings.py
bayesline/api/_src/equity/upload.py
bayesline/api/_src/equity/report/accessor.py
bayesline/api/_src/equity/report/api.py
bayesline/api/_src/equity/report/api_loader.py
bayesline/api/_src/equity/report/covariance.py
bayesline/api/_src/equity/report/exposure.py
bayesline/api/_src/equity/report/factor_stats.py
bayesline/api/_src/equity/report/settings.py
bayesline/api/_src/equity/report/universe.py
bayesline/api/equity/__init__.py
bayesline_api-0.11.0.dist-info/METADATA
bayesline_api-0.11.0.dist-info/WHEEL
bayesline_api-0.11.0.dist-info/RECORD
