Metadata-Version: 2.4
Name: bayesline-api
Version: 0.11.0
Requires-Python: <4,>=3.10
Requires-Dist: polars<2,>=1.23.0
Requires-Dist: pydantic<3,>=2.6.3
Provides-Extra: gpu
